aws_cost_optimization_9/__init__.py
aws_cost_optimization_9/_cloudwatch_costing.py
aws_cost_optimization_9/_ec2_costing.py
aws_cost_optimization_9/_elb_costing.py
aws_cost_optimization_9/_kms_costing.py
aws_cost_optimization_9/_rds_costing.py
aws_cost_optimization_9/_ri_recommendations.py
aws_cost_optimization_9/_savings_plan.py
aws_cost_optimization_9/utils.py
aws_cost_optimization_9-0.2.8.dist-info/LICENCE
aws_cost_optimization_9-0.2.8.dist-info/METADATA
aws_cost_optimization_9-0.2.8.dist-info/WHEEL
aws_cost_optimization_9-0.2.8.dist-info/top_level.txt
aws_cost_optimization_9-0.2.8.dist-info/RECORD
